AUTHORS.rst
CONTRIBUTING.rst
HISTORY.rst
LICENSE
MANIFEST.in
README.rst
setup.cfg
setup.py
django_admin_user_summary/__init__.py
django_admin_user_summary/admin.py
django_admin_user_summary/apps.py
django_admin_user_summary/models.py
django_admin_user_summary.egg-info/PKG-INFO
django_admin_user_summary.egg-info/SOURCES.txt
django_admin_user_summary.egg-info/dependency_links.txt
django_admin_user_summary.egg-info/not-zip-safe
django_admin_user_summary.egg-info/requires.txt
django_admin_user_summary.egg-info/top_level.txt
django_admin_user_summary/migrations/0001_initial.py
django_admin_user_summary/migrations/__init__.py
django_admin_user_summary/templates/admin/user_summary_change_list.html