Metadata-Version: 1.1
Name: django-admin-user-summary
Version: 0.1.0
Summary: UNKNOWN
Home-page: https://github.com/affinitydigital/django-admin-user-summary
Author: Ivan Markeev
Author-email: markeev@gmail.com
License: Apache Software License 2.0
Keywords: django-admin-user-summary
Platform: UNKNOWN
Classifier: Development Status :: 3 - Alpha
Classifier: Framework :: Django :: 1.11
Classifier: Framework :: Django :: 2.0
Classifier: Intended Audience :: Developers
Classifier: License :: OSI Approved :: BSD License
Classifier: Natural Language :: English
Classifier: Programming Language :: Python :: 3
Classifier: Programming Language :: Python :: 3.4
Classifier: Programming Language :: Python :: 3.5
Classifier: Programming Language :: Python :: 3.6
